polycleaver/__init__.py
polycleaver/core/__init__.py
polycleaver/core/miscellaneous.py
polycleaver/core/mnx.py
polycleaver/core/mx.py
polycleaver/core/tools.py
polycleaver-0.0.8.dist-info/LICENSE
polycleaver-0.0.8.dist-info/METADATA
polycleaver-0.0.8.dist-info/WHEEL
polycleaver-0.0.8.dist-info/top_level.txt
polycleaver-0.0.8.dist-info/RECORD
