Metadata-Version: 2.1
Name: polycleaver
Version: 0.0.8
Summary: Package for the generation of non-polar and stoichiometric surfaces from ionic structures.
Author: Eric Mates-Torres
Author-email: <eric.mates@uab.cat>
Keywords: python,slab,surface,miller,ionic,mineral
Classifier: Development Status :: 1 - Planning
Classifier: Intended Audience :: Developers
Classifier: Programming Language :: Python :: 3
Classifier: Operating System :: Unix
Classifier: Operating System :: MacOS :: MacOS X
Classifier: Operating System :: Microsoft :: Windows
License-File: LICENSE
Requires-Dist: pymatgen
